polymonitor/__init__.py
polymonitor/__main__.py
polymonitor/cli.py
polymonitor-0.1.6.dist-info/entry_points.txt
polymonitor-0.1.6.dist-info/WHEEL
polymonitor-0.1.6.dist-info/METADATA
polymonitor-0.1.6.dist-info/RECORD
