Metadata-Version: 2.1
Name: polymonitor
Version: 0.1.6
Summary: Polymonitor can be used as a stand alone CLI tool to quickly check the status of a URL or as a plugin for polybar.
Home-page: https://github.com/hegelocampus/polymonitor
License: MIT
Author: Bee
Author-email: bellis8099@gmail.com
Requires-Python: >=3.8,<4.0
Classifier: License :: OSI Approved :: MIT License
Classifier: Programming Language :: Python :: 3
Classifier: Programming Language :: Python :: 3.8
Requires-Dist: argparse (>=1.4.0,<2.0.0)
Requires-Dist: requests (>=2.24.0,<3.0.0)
Requires-Dist: termcolor (>=1.1.0,<2.0.0)
Requires-Dist: validators (>=0.17.1,<0.18.0)
